sgr_schema/SGrIncluder.xsd
sgr_schema/__init__.py
sgr_schema/Communicator/CommunicatorFrame.xsd
sgr_schema/Communicator/CommunicatorTypes.xsd
sgr_schema/Communicator/Includer.xsd
sgr_schema/FunctionalProfile/FunctionalProfileFrame.xsd
sgr_schema/FunctionalProfile/Includer.xsd
sgr_schema/Generic/BaseType_FunctionalProfileCategory.xsd
sgr_schema/Generic/BaseType_LevelOfOperationType.xsd
sgr_schema/Generic/BaseTypes.xsd
sgr_schema/Generic/DataPoint.xsd
sgr_schema/Generic/FunctionalProfile.xsd
sgr_schema/Generic/GenericAttribute.xsd
sgr_schema/Generic/SGrSerialIntCapability.xsd
sgr_schema/Product/ContactInterface.xsd
sgr_schema/Product/GenericInterface.xsd
sgr_schema/Product/Includer.xsd
sgr_schema/Product/MessagingInterface.xsd
sgr_schema/Product/MessagingTypes.xsd
sgr_schema/Product/ModbusInterface.xsd
sgr_schema/Product/ModbusTypes.xsd
sgr_schema/Product/Product.xsd
sgr_schema/Product/RestApiInterface.xsd
sgr_schema/Product/RestApiTypes.xsd
sgr_specification/__init__.py
sgr_specification/v0/__init__.py
sgr_specification/v0/communicator/__init__.py
sgr_specification/v0/communicator/communicator_frame.py
sgr_specification/v0/communicator/communicator_types.py
sgr_specification/v0/functional_profile/__init__.py
sgr_specification/v0/functional_profile/functional_profile_frame.py
sgr_specification/v0/generic/__init__.py
sgr_specification/v0/generic/base_type_functional_profile_category.py
sgr_specification/v0/generic/base_type_level_of_operation_type.py
sgr_specification/v0/generic/base_types.py
sgr_specification/v0/generic/data_point.py
sgr_specification/v0/generic/functional_profile.py
sgr_specification/v0/generic/generic_attribute.py
sgr_specification/v0/generic/sgr_serial_int_capability.py
sgr_specification/v0/product/__init__.py
sgr_specification/v0/product/contact_interface.py
sgr_specification/v0/product/generic_interface.py
sgr_specification/v0/product/messaging_interface.py
sgr_specification/v0/product/messaging_types.py
sgr_specification-2.1.20250902.dist-info/licenses/LICENSE.md
sgr_specification-2.1.20250902.dist-info/METADATA
sgr_specification-2.1.20250902.dist-info/WHEEL
sgr_specification-2.1.20250902.dist-info/top_level.txt
sgr_specification-2.1.20250902.dist-info/RECORD
