Metadata-Version: 2.4
Name: sgr-specification
Version: 2.1.20250902
Summary: SmartGridready Specification Library
Author: Robin Schoch, Matthias Krebs
Maintainer: Matthias Krebs
License-Expression: BSD-3-Clause
Project-URL: Homepage, https://www.smartgridready.ch/
Project-URL: Documentation, https://smartgridready.github.io/
Project-URL: Repository, https://github.com/SmartGridready/SGrSpecification.git
Project-URL: Issues, https://github.com/SmartGridready/SGrSpecification/issues
Project-URL: Changelog, https://github.com/SmartGridready/SGrPython/blob/master/specification/CHANGELOG.md
Requires-Python: >=3.9
License-File: LICENSE.md
Dynamic: license-file
